mkctf/__init__.py
mkctf/__version__.py
mkctf/cli.py
mkctf/monitor.py
mkctf/api/__init__.py
mkctf/api/challenge.py
mkctf/api/repository.py
mkctf/api/config/__init__.py
mkctf/api/config/_base.py
mkctf/api/config/challenge.py
mkctf/api/config/general.py
mkctf/api/config/repository.py
mkctf/command/__init__.py
mkctf/command/build.py
mkctf/command/configure.py
mkctf/command/create.py
mkctf/command/delete.py
mkctf/command/deploy.py
mkctf/command/disable.py
mkctf/command/enable.py
mkctf/command/enum.py
mkctf/command/export.py
mkctf/command/healthcheck.py
mkctf/command/init.py
mkctf/command/push.py
mkctf/command/renew_flag.py
mkctf/command/update_meta.py
mkctf/helper/__init__.py
mkctf/helper/argparse.py
mkctf/helper/checksum.py
mkctf/helper/cli.py
mkctf/helper/display.py
mkctf/helper/exception.py
mkctf/helper/logging.py
mkctf/helper/random.py
mkctf/helper/signal.py
mkctf/helper/subprocess.py
mkctf/monitoring/__init__.py
mkctf/monitoring/monitor.py
mkctf/monitoring/notifier.py
mkctf/monitoring/task.py
mkctf/wizard/__init__.py
mkctf/wizard/_base.py
mkctf/wizard/challenge.py
mkctf/wizard/repository.py
mkctf-7.0.7.dist-info/licenses/LICENSE
mkctf-7.0.7.dist-info/METADATA
mkctf-7.0.7.dist-info/WHEEL
mkctf-7.0.7.dist-info/entry_points.txt
mkctf-7.0.7.dist-info/top_level.txt
mkctf-7.0.7.dist-info/RECORD
