Metadata-Version: 2.4
Name: mkctf
Version: 7.0.7
Summary: MaKe Capture The Flag
Author-email: koromodako <koromodako@gmail.com>
License-Expression: MIT
Project-URL: Homepage, https://github.com/koromodako/mkctf
Project-URL: Repository, https://github.com/koromodako/mkctf
Project-URL: Bug Tracker, https://github.com/koromodako/mkctf/issues
Keywords: ctf,framework,cli
Classifier: Development Status :: 5 - Production/Stable
Classifier: Intended Audience :: Developers
Classifier: Intended Audience :: End Users/Desktop
Classifier: Natural Language :: English
Classifier: Operating System :: OS Independent
Classifier: Programming Language :: Python :: 3
Classifier: Programming Language :: Python :: 3 :: Only
Classifier: Topic :: Security
Classifier: Topic :: Utilities
Requires-Python: >=3.10
License-File: LICENSE
Requires-Dist: pick~=2.0
Requires-Dist: rich~=13.6
Requires-Dist: jinja2~=3.1
Requires-Dist: aiohttp~=3.9
Requires-Dist: humanize~=4.0
Requires-Dist: ruamel.yaml~=0.17
Requires-Dist: python-slugify~=8.0
Dynamic: license-file
